dod/__init__.py
dod/_base.py
dod-0.0.3.dist-info/LICENSE
dod-0.0.3.dist-info/METADATA
dod-0.0.3.dist-info/WHEEL
dod-0.0.3.dist-info/top_level.txt
dod-0.0.3.dist-info/RECORD
